textagents/__init__.py
textagents/agent.py
textagents/cli.py
textagents/errors.py
textagents/input_handler.py
textagents/loader.py
textagents/model_builder.py
textagents/parser.py
textagents/py.typed
textagents/validator_builder.py
textagents-0.0.1.dist-info/WHEEL
textagents-0.0.1.dist-info/entry_points.txt
textagents-0.0.1.dist-info/METADATA
textagents-0.0.1.dist-info/RECORD
