Metadata-Version: 2.4
Name: textagents
Version: 0.0.1
Summary: Declarative, file-based PydanticAI agents
Keywords: llm,pydantic,agents,evaluation,judge,pydantic-ai
Author: Jan Siml
Author-email: Jan Siml <49557684+svilupp@users.noreply.github.com>
License-Expression: MIT
Classifier: Development Status :: 3 - Alpha
Classifier: Intended Audience :: Developers
Classifier: License :: OSI Approved :: MIT License
Classifier: Programming Language :: Python :: 3
Classifier: Programming Language :: Python :: 3.11
Classifier: Programming Language :: Python :: 3.12
Classifier: Programming Language :: Python :: 3.13
Classifier: Topic :: Software Development :: Libraries
Classifier: Typing :: Typed
Requires-Dist: pydantic>=2.0
Requires-Dist: pydantic-ai>=0.1.0
Requires-Dist: python-dotenv>=1.2.1
Requires-Dist: textprompts>=0.1.0
Requires-Dist: typer>=0.9.0
Requires-Dist: pytest>=8.0 ; extra == 'dev'
Requires-Dist: pytest-asyncio>=0.23 ; extra == 'dev'
Requires-Dist: pytest-cov>=4.0 ; extra == 'dev'
Requires-Dist: ty ; extra == 'dev'
Requires-Dist: ruff>=0.1.0 ; extra == 'dev'
Requires-Dist: mkdocs>=1.6 ; extra == 'docs'
Requires-Dist: mkdocs-material>=9.5 ; extra == 'docs'
Requires-Dist: mkdocstrings[python]>=0.27 ; extra == 'docs'
Requires-Dist: logfire>=0.1.0 ; extra == 'logfire'
Requires-Python: >=3.11
Provides-Extra: dev
Provides-Extra: docs
Provides-Extra: logfire
